callisto_jupyter_d1-0.0.18.data/scripts/jupyter_d1_install_kernels
callisto_jupyter_d1-0.0.18.data/scripts/jupyter_d1_test
callisto_jupyter_d1-0.0.18.data/scripts/start_jupyter_d1
jupyter_d1/__init__.py
jupyter_d1/commands.py
jupyter_d1/d1_response.py
jupyter_d1/dav.py
jupyter_d1/dav_auth.py
jupyter_d1/deps.py
jupyter_d1/logger.py
jupyter_d1/main.py
jupyter_d1/security.py
jupyter_d1/settings.py
jupyter_d1/utils.py
jupyter_d1/uvicorn_worker.py
jupyter_d1/version.py
jupyter_d1/dependency/__init__.py
jupyter_d1/dependency/dependency_manager.py
jupyter_d1/dependency/python/__init__.py
jupyter_d1/dependency/python/dependency_manager.py
jupyter_d1/dependency/python/startup/__init__.py
jupyter_d1/dependency/python/startup/dependency_startup.py
jupyter_d1/dependency/r/__init__.py
jupyter_d1/dependency/r/dependency_manager.py
jupyter_d1/kernels/__init__.py
jupyter_d1/kernels/dependency_checker.py
jupyter_d1/kernels/kernel_definition.py
jupyter_d1/kernels/vars_manager.py
jupyter_d1/kernels/workdir_manager.py
jupyter_d1/kernels/python/__init__.py
jupyter_d1/kernels/python/dependency_checker.py
jupyter_d1/kernels/python/import_to_lib.py
jupyter_d1/kernels/python/vars_manager.py
jupyter_d1/kernels/python/workdir_manager.py
jupyter_d1/kernels/python/startup/__init__.py
jupyter_d1/kernels/python/startup/callisto_startup.py
jupyter_d1/kernels/r/__init__.py
jupyter_d1/kernels/r/vars_manager.py
jupyter_d1/kernels/r/workdir_manager.py
jupyter_d1/kernels/zsh/__init__.py
jupyter_d1/kernels/zsh/vars_manager.py
jupyter_d1/kernels/zsh/workdir_manager.py
jupyter_d1/models/JSONType.py
jupyter_d1/models/__init__.py
jupyter_d1/models/base_wrapper.py
jupyter_d1/models/cell.py
jupyter_d1/models/code_complete.py
jupyter_d1/models/data_remote.py
jupyter_d1/models/dependency.py
jupyter_d1/models/environment_info.py
jupyter_d1/models/execution_state.py
jupyter_d1/models/kernel.py
jupyter_d1/models/kernel_message.py
jupyter_d1/models/kernel_spec.py
jupyter_d1/models/kernel_variable.py
callisto_jupyter_d1-0.0.18.dist-info/METADATA
callisto_jupyter_d1-0.0.18.dist-info/WHEEL
callisto_jupyter_d1-0.0.18.dist-info/top_level.txt
callisto_jupyter_d1-0.0.18.dist-info/RECORD
