Metadata-Version: 2.1
Name: callisto-jupyter-d1
Version: 0.0.18
Summary: Jupyter D1 Server for Callisto
Home-page: https://callistoapp.com
Author: Oak City Labs
Author-email: team@oakcity.io
Classifier: Programming Language :: Python :: 3
Classifier: License :: OSI Approved :: MIT License
Classifier: Operating System :: OS Independent
Requires-Python: >=3.6
Requires-Dist: wsgidav (<5,>=4.0.1)
Requires-Dist: fastapi (<1,>=0.52.0)
Requires-Dist: asyncblink (<1,>=0.3.2)
Requires-Dist: blinker (<1.6,>=1.3)
Requires-Dist: uvicorn (<1,>=0.11.3)
Requires-Dist: websockets (>=10.0)
Requires-Dist: httptools (>=0.4.0)
Requires-Dist: python-dotenv (<1,>=0.13.0)
Requires-Dist: nbformat (<6,>=5.0.4)
Requires-Dist: python-jose (<4,>=3.1.0)
Requires-Dist: jsonpatch (<2,>=1.32)
Requires-Dist: jupyter (<2,>=1.0.0)
Requires-Dist: jupyter-client (<8,>=7)
Requires-Dist: jupyter-console (<7,>=6.1.0)
Requires-Dist: jupyter-core (<5,>=4.6.3)
Requires-Dist: jupyter-kernel-gateway (<3,>=2.4.0)
Requires-Dist: zsh-jupyter-kernel (>=3.2)
Requires-Dist: bash-kernel (>=0.7.2)
Requires-Dist: pynvml (<9,>=8.0.4)
Requires-Dist: callisto-python (<1,>=0.0.8)
Requires-Dist: jupytext (<2,>=1.13.8)
Requires-Dist: python-multipart (<1,>=0.0.5)
Requires-Dist: importlib-resources (==5.10.2)
Provides-Extra: full
Requires-Dist: psutil (<6,>=5.7.2) ; extra == 'full'
Provides-Extra: watchdog
Requires-Dist: callisto-watchdog (<1,>=0.0.1) ; extra == 'watchdog'
